{
  "VanillaUpgrades.dll": {
    "name": "Vanilla Upgrades",
    "description": "Improves the vanilla expierience by adding quality of life features",
    "author": "NeptuneSky",
    "version": "5.3"
  },
  "ANAIS.dll": {
    "name": "ANAIS",
    "description": "Replaces the stock navigation system with a more elaborated one",
    "author": "Altiar",
    "version": "1.4.2"
  },
  "Texturable.dll": {
    "name": "Textureable",
    "description": "Makes more parts texturable like parachutes, docking ports and all of that",
    "author": "NeptuneSky",
    "version": "0.2.1-beta"
  },
  "AeroTrajectory.dll": {
    "name": "Aero Trajectory",
    "description": "Shows you the trajectory you will have in an atmosphere",
    "author": "AstroTheRabbit",
    "version": "1.4"
  },
  "PartEditor.dll": {
    "name": "Part Editor",
    "description": "It is bp editing in game",
    "author": "Cucumber Space",
    "version": "1.0"
  },
  "ThrustAssistMod.dll": {
    "name": "Thrust Assist",
    "description": "It helps you land and land at a target",
    "author": "Darthan",
    "version": "0.7"
  },
  "ActionGroupsMod.dll": {
    "name": "Action Groups Mod",
    "description": "Adds KSP like Action Groups to SFS",
    "author": "AstroTheRabbit",
    "version": "1.3",
    "dependencies": [
      "CustomSaveData.dll"
    ]
  },
  "CustomSaveData.dll": {
    "name": "Custom Save Data",
    "description": "A Mod that allows for the saving and loading of custom modded data to rockets and blueprints",
    "author": "AstroTheRabbit",
    "version": "1.0"
  },
  "SmartSASMod.dll": {
    "name": "Smart SAS",
    "description": "Adds Smart SAS that is able to lock onto Prograde, Retrograde, Surface and Target Nodes",
    "author": "AstroTheRabbit",
    "version": "1.7"
  }
}